{
  "protocols_tvl": "TVL",
  "chains_tvl": "CHAIN_TVL",
  "protocols_mcap": "MC",
  "protocols_fdv": "FDMC",
  "protocols_staking": "STAKING",
  "protocols_borrowed": "BORROWED",
  "protocols_pool2": "POOL2",
  "protocols_change_1h": "CHANGE_1H",
  "protocols_change_1d": "CHANGE_1D",
  "protocols_change_7d": "CHANGE_7D",
  "fees_total24h": "FEES_24H",
  "fees_total7d": "FEES_7D",
  "fees_total30d": "FEES_30D",
  "fees_total1y": "FEES_1Y",
  "fees_totalAllTime": "FEES_ALL_TIME",
  "fees_dailyRevenue": "REVENUE_24H",
  "fees_dailyProtocolRevenue": "PROTOCOL_REVENUE_24H",
  "fees_dailySupplySideRevenue": "SUPPLY_SIDE_REVENUE_24H",
  "fees_dailyUserFees": "USER_FEES_24H",
  "fees_dailyHoldersRevenue": "HOLDERS_REVENUE_24H",
  "fees_average1y": "FEES_AVERAGE_1Y",
  "fees_change_1d": "FEES_CHANGE_1D",
  "fees_change_7d": "FEES_CHANGE_7D",
  "fees_change_1m": "FEES_CHANGE_1M",
  "dexs_total24h": "DEX_VOLUME_24H",
  "dexs_total7d": "DEX_VOLUME_7D",
  "dexs_total30d": "DEX_VOLUME_30D",
  "dexs_totalAllTime": "DEX_VOLUME_ALL_TIME",
  "dexs_change_1d": "DEX_CHANGE_1D",
  "dexs_change_7d": "DEX_CHANGE_7D",
  "dexs_change_1m": "DEX_CHANGE_1M",
  "derivatives_total24h": "DERIVATIVES_VOLUME_24H",
  "derivatives_total7d": "DERIVATIVES_VOLUME_7D",
  "derivatives_total30d": "DERIVATIVES_VOLUME_30D",
  "derivatives_change_1d": "DERIVATIVES_CHANGE_1D",
  "derivatives_change_7d": "DERIVATIVES_CHANGE_7D",
  "options_total24h": "OPTIONS_VOLUME_24H",
  "options_total7d": "OPTIONS_VOLUME_7D",
  "options_total30d": "OPTIONS_VOLUME_30D",
  "options_dailyNotionalVolume": "OPTIONS_NOTIONAL_24H",
  "options_dailyPremiumVolume": "OPTIONS_PREMIUM_24H",
  "aggregators_total24h": "AGGREGATOR_VOLUME_24H",
  "aggregators_total7d": "AGGREGATOR_VOLUME_7D",
  "aggregators_total30d": "AGGREGATOR_VOLUME_30D",
  "bridges_lastDailyVolume": "BRIDGE_VOLUME_24H",
  "bridges_weeklyVolume": "BRIDGE_VOLUME_7D",
  "bridges_monthlyVolume": "BRIDGE_VOLUME_30D",
  "stablecoins_circulating_peggedUSD": "STABLECOIN_SUPPLY",
  "stablecoins_circulatingPrevDay_peggedUSD": "STABLECOIN_SUPPLY_PREV_DAY",
  "stablecoins_circulatingPrevWeek_peggedUSD": "STABLECOIN_SUPPLY_PREV_WEEK",
  "stablecoins_price": "STABLECOIN_PRICE"
}